examsage/__init__.py
examsage/assessment.py
examsage/body.py
examsage/course.py
examsage/finitetiles.py
examsage/headfoot.py
examsage/instructions.py
examsage/lib.py
examsage/mathlib.py
examsage/newpagemessage.py
examsage/problem.py
examsage/problemset.py
examsage/pyvars.py
examsage/section.py
examsage/ztable.py
examsage-0.0.1.dev2.data/scripts/makeproblem.py
examsage-0.0.1.dev2.data/scripts/newproblem.py
examsage-0.0.1.dev2.dist-info/LICENSE.md
examsage-0.0.1.dev2.dist-info/METADATA
examsage-0.0.1.dev2.dist-info/WHEEL
examsage-0.0.1.dev2.dist-info/top_level.txt
examsage-0.0.1.dev2.dist-info/RECORD
