Metadata-Version: 2.1
Name: examsage
Version: 0.0.1.dev2
Summary: ExamSage is a Python package for generating math problems in $LaTeX$. The goal of this project is to allow math instructors to create randomizable math problems and assessments without extensive programming knowledge.
Home-page: https://pypi.org/project/examsage/
Author: Michael Barnard
Author-email: mbarnard10@ivytech.edu
License: MIT
Platform: UNKNOWN
Classifier: Programming Language :: Python :: 3
Classifier: License :: OSI Approved :: MIT License
Classifier: Operating System :: OS Independent
